<?xml version="1.0" encoding="utf-8" ?>
<dwsync>
<file name="dashboard.php" local="130764711280466009" remote="130764783000000000" testing="130764783000000000" />
<file name="debug_log.php" local="130763623270690424" remote="130764742800000000" testing="130764742800000000" />
<file name="error.php" local="130763623270980441" remote="130764742800000000" testing="130764742800000000" />
<file name="forgot_password.php" local="130764669194904116" remote="130764742800000000" testing="130764742800000000" />
<file name="index.php" local="130764669195104117" remote="130764742800000000" testing="130764742800000000" />
<file name="setup.sql" local="130763623271870492" remote="130764743400000000" testing="130764743400000000" />
<file name="club_edit.php" local="130764679739072675" remote="130764751200000000" testing="130764751200000000" />
<file name="club_list.php" local="130764669194404116" remote="130764741000000000" testing="130764741000000000" />
<file name="orders_list.php" local="130764676993301128" remote="130764748800000000" testing="130764748800000000" />
<file name="orders_edit.php" local="130764669195504117" remote="130764742800000000" testing="130764742800000000" />
<file name="club_list-original.php" local="130764669193804115" remote="130764741000000000" testing="130764741000000000" />
<file name="list-and-page-template.zip" local="130764543807203735" remote="130764742800000000" testing="130764742800000000" />
<file name="quickstart_base.zip" local="130764667593031733" remote="130764743400000000" testing="130764743400000000" />
<file name="error_log" local="130764683595871956" remote="130764755400000000" testing="130764755400000000" />
<file name="payment_edit.php" local="130764696364415159" remote="130764768000000000" testing="130764768000000000" />
<file name="payment_list.php" local="130764708255108108" remote="130764780000000000" testing="130764780000000000" />
<file name="promo_edit.php" local="130764711843621250" remote="130764783600000000" testing="130764783600000000" />
<file name="promo_list.php" local="130764711902277353" remote="130764783600000000" testing="130764783600000000" />
</dwsync>